{
  "$schema": "https://frontmatter.codes/frontmatter.schema.json",
  "frontMatter.taxonomy.fieldGroups": [
    {
      "id": "resources",
      "labelField": "Resources",
      "fields": [
        {
          "title": "Name",
          "name": "name",
          "type": "string",
          "single": true
        },
        {
          "title": "Source",
          "name": "src",
          "type": "image"
        }
      ]
    }
  ],
  "frontMatter.taxonomy.contentTypes": [
    {
      "name": "default",
      "pageBundle": false,
      "previewPath": null,
      "fields": [
        {
          "title": "Title",
          "name": "title",
          "type": "string"
        },
        {
          "title": "Description",
          "name": "description",
          "type": "string"
        },
        {
          "title": "Publishing date",
          "name": "date",
          "type": "datetime",
          "default": "{{now}}",
          "isPublishDate": true
        },
        {
          "title": "Tags",
          "name": "tags",
          "type": "tags"
        },
        {
          "title": "Categories",
          "name": "categories",
          "type": "categories"
        },
        {
          "title": "Resources",
          "name": "resources",
          "type": "block",
          "fieldGroup": [
            "resources"
          ]
        },
        {
          "title": "Is in draft",
          "name": "draft",
          "type": "draft"
        },
        {
          "title": "Light gallery",
          "name": "lightgallery",
          "type": "boolean"
        }
      ]
    }
  ],
  "frontMatter.framework.id": "hugo",
  "frontMatter.content.publicFolder": "assets",
  "frontMatter.preview.host": "http://localhost:1313",
  "frontMatter.content.pageFolders": [
    {
      "title": "Content",
      "path": "[[workspace]]/content",
      "excludeSubdir": true
    },
    {
      "title": "About",
      "path": "[[workspace]]/content/about"
    },
    {
      "title": "Posts",
      "path": "[[workspace]]/content/posts"
    }
  ],
  "frontMatter.dashboard.openOnStart": true
}